taylor_series_linear_attention/__init__.py
taylor_series_linear_attention/attention.py
taylor_series_linear_attention/tensor_typing.py
taylor_series_linear_attention/vit.py
taylor_series_linear_attention-0.1.12.dist-info/LICENSE
taylor_series_linear_attention-0.1.12.dist-info/METADATA
taylor_series_linear_attention-0.1.12.dist-info/WHEEL
taylor_series_linear_attention-0.1.12.dist-info/top_level.txt
taylor_series_linear_attention-0.1.12.dist-info/RECORD
