Metadata-Version: 2.1
Name: taylor-series-linear-attention
Version: 0.1.12
Summary: Taylor Series Linear Attention
Home-page: https://github.com/lucidrains/taylor-series-linear-attention
Author: Phil Wang
Author-email: lucidrains@gmail.com
License: MIT
Keywords: artificial intelligence,deep learning,attention mechanism
Classifier: Development Status :: 4 - Beta
Classifier: Intended Audience :: Developers
Classifier: Topic :: Scientific/Engineering :: Artificial Intelligence
Classifier: License :: OSI Approved :: MIT License
Classifier: Programming Language :: Python :: 3.6
License-File: LICENSE
Requires-Dist: einops >=0.7.0
Requires-Dist: jaxtyping
Requires-Dist: rotary-embedding-torch >=0.5.3
Requires-Dist: torch >=2.0
